pycorrelation/__init__.py
pycorrelation/correl.py
pycorrelation/symmetric_matrix.py
pycorrelation-0.0.2.dist-info/METADATA
pycorrelation-0.0.2.dist-info/WHEEL
pycorrelation-0.0.2.dist-info/licenses/LICENSE
pycorrelation-0.0.2.dist-info/RECORD
