Metadata-Version: 2.3
Name: pycorrelation
Version: 0.0.2
Summary: PyCorrelation is a Python package designed to handle symmetric and correlation matrices efficiently.
Project-URL: Homepage, https://github.com/SRKX/pycorrelation
Project-URL: Issues, https://github.com/SRKX/pycorrelation/issues
Author-email: Jeremie Smaga <jeremie@smaga.ch>
License-File: LICENSE
Classifier: License :: OSI Approved :: MIT License
Classifier: Operating System :: OS Independent
Classifier: Programming Language :: Python :: 3
Requires-Python: >=3.9
